chess_com-3.13.0.dist-info/licenses/LICENSE.txt
chessdotcom/__init__.py
chessdotcom/aio.py
chessdotcom/client.py
chessdotcom/errors.py
chessdotcom/response_builder.py
chessdotcom/utils.py
chessdotcom/endpoints/__init__.py
chessdotcom/endpoints/club_details.py
chessdotcom/endpoints/club_matches.py
chessdotcom/endpoints/club_members.py
chessdotcom/endpoints/country_clubs.py
chessdotcom/endpoints/country_details.py
chessdotcom/endpoints/country_players.py
chessdotcom/endpoints/current_daily_puzzle.py
chessdotcom/endpoints/leaderboards.py
chessdotcom/endpoints/player_clubs.py
chessdotcom/endpoints/player_current_games.py
chessdotcom/endpoints/player_current_games_to_move.py
chessdotcom/endpoints/player_game_archives.py
chessdotcom/endpoints/player_games_by_basetime_increment.py
chessdotcom/endpoints/player_games_by_month.py
chessdotcom/endpoints/player_games_by_month_pgn.py
chessdotcom/endpoints/player_profile.py
chessdotcom/endpoints/player_stats.py
chessdotcom/endpoints/player_team_matches.py
chessdotcom/endpoints/player_tournaments.py
chessdotcom/endpoints/random_daily_puzzle.py
chessdotcom/endpoints/streamers.py
chessdotcom/endpoints/team_match.py
chessdotcom/endpoints/team_match_board.py
chessdotcom/endpoints/team_match_live.py
chessdotcom/endpoints/team_match_live_board.py
chessdotcom/endpoints/titled_players.py
chessdotcom/endpoints/tournament_details.py
chessdotcom/endpoints/tournament_round.py
chessdotcom/endpoints/tournament_round_group_details.py
chess_com-3.13.0.dist-info/METADATA
chess_com-3.13.0.dist-info/WHEEL
chess_com-3.13.0.dist-info/top_level.txt
chess_com-3.13.0.dist-info/RECORD
