Metadata-Version: 2.4
Name: chess.com
Version: 3.13.0
Summary: Python client for Chess.com API
Author-email: Artur Saradzhyan <sarartur.ruk@gmail.com>
License: MIT License
Project-URL: Homepage, https://github.com/sarartur/chess.com
Project-URL: Documentation, https://chesscom.readthedocs.io
Keywords: chess,chess.com
Classifier: Programming Language :: Python :: 3
Classifier: License :: OSI Approved :: MIT License
Classifier: Operating System :: OS Independent
Requires-Python: >=3.8
License-File: LICENSE.txt
Requires-Dist: aiohttp>=3
Requires-Dist: requests>=2
Dynamic: license-file
